<?xml version="1.0" encoding="UTF-8"?>
<node>
<version>6</version>
<dict>
  <key>title</key><string>python</string>
  <key>nodeid</key><string>3954585b-ff48-4696-aa09-a7dd9a813bae</string>
  <key>modified_time</key><integer>1552485360</integer>
  <key>version</key><integer>6</integer>
  <key>content_type</key><string>text/xhtml+xml</string>
  <key>created_time</key><integer>1524485493</integer>
  <key>info_sort_dir</key><integer>1</integer>
  <key>order</key><integer>18</integer>
  <key>info_sort</key><string>order</string>
</dict>
</node>
